unicorn_baseline/__init__.py
unicorn_baseline/inference.py
unicorn_baseline/io.py
unicorn_baseline/language/__init__.py
unicorn_baseline/language/main.py
unicorn_baseline/language/task_definitions.py
unicorn_baseline/vision/__init__.py
unicorn_baseline/vision/main.py
unicorn_baseline/vision/pathology/__init__.py
unicorn_baseline/vision/pathology/dataset.py
unicorn_baseline/vision/pathology/feature_extraction.py
unicorn_baseline/vision/pathology/main.py
unicorn_baseline/vision/pathology/model_utils.py
unicorn_baseline/vision/pathology/models.py
unicorn_baseline/vision/pathology/wsi.py
unicorn_baseline/vision/pathology/wsi_utils.py
unicorn_baseline/vision/pathology/titan/__init__.py
unicorn_baseline/vision/pathology/titan/conch_v1_5.py
unicorn_baseline/vision/pathology/titan/configuration_titan.py
unicorn_baseline/vision/pathology/titan/modeling_titan.py
unicorn_baseline/vision/pathology/titan/vision_transformer.py
unicorn_baseline/vision/radiology/__init__.py
unicorn_baseline/vision/radiology/dataset.py
unicorn_baseline/vision/radiology/main.py
unicorn_baseline/vision/radiology/patch_extraction.py
unicorn_baseline/vision/radiology/models/__init__.py
unicorn_baseline/vision/radiology/models/ctfm.py
unicorn_baseline/vision/radiology/models/mrsegmentator.py
unicorn_baseline/vision/radiology/models/smalldinov2.py
unicorn_baseline/vision_language/__init__.py
unicorn_baseline/vision_language/inference.py
unicorn_baseline/vision_language/main.py
unicorn_baseline/vision_language/models.py
unicorn_baseline/vision_language/prism/__init__.py
unicorn_baseline/vision_language/prism/biogpt.py
unicorn_baseline/vision_language/prism/biogpt_hf.py
unicorn_baseline/vision_language/prism/configuring_prism.py
unicorn_baseline/vision_language/prism/memory_test.py
unicorn_baseline/vision_language/prism/modeling_prism.py
unicorn_baseline/vision_language/prism/perceiver.py
unicorn_baseline-1.4.4.dist-info/licenses/LICENSE
unicorn_baseline-1.4.4.dist-info/METADATA
unicorn_baseline-1.4.4.dist-info/WHEEL
unicorn_baseline-1.4.4.dist-info/entry_points.txt
unicorn_baseline-1.4.4.dist-info/top_level.txt
unicorn_baseline-1.4.4.dist-info/RECORD
