Metadata-Version: 2.4
Name: unicorn_baseline
Version: 1.4.4
Summary: Baseline inference algorithm for the UNICORN Challenge
Home-page: https://github.com/DIAGNijmegen/unicorn_baseline
Author: Joeran Bosma, Clément Grisi, Marina D`Amato, Luc Builtjes, Lena Philipp, Fennie van der Graaf, Judith Lefkes, Michelle Stegeman, Rianne Weber
Author-email: Clement.Grisi@radboudumc.nl
Project-URL: Bug Tracker, https://github.com/DIAGNijmegen/unicorn_baseline/issues
Platform: unix
Platform: linux
Platform: osx
Platform: cygwin
Platform: win32
Classifier: Programming Language :: Python :: 3
Classifier: Programming Language :: Python :: 3 :: Only
Classifier: Programming Language :: Python :: 3.10
Classifier: Programming Language :: Python :: 3.11
Classifier: Programming Language :: Python :: 3.12
Classifier: Programming Language :: Python :: 3.13
Requires-Python: >=3.10
License-File: LICENSE
Requires-Dist: torch
Requires-Dist: numpy<2
Requires-Dist: pandas
Requires-Dist: pillow
Requires-Dist: tqdm
Requires-Dist: numba
Requires-Dist: torchvision
Requires-Dist: opencv-python
Requires-Dist: matplotlib
Requires-Dist: wholeslidedata<0.0.16
Requires-Dist: timm
Requires-Dist: torch
Requires-Dist: transformers
Requires-Dist: environs
Requires-Dist: sacremoses
Requires-Dist: einops
Requires-Dist: einops-exts
Requires-Dist: safetensors
Requires-Dist: scipy
Requires-Dist: SimpleITK
Requires-Dist: Pillow
Requires-Dist: llm_extractinator
Provides-Extra: testing
Requires-Dist: pytest>=6.0; extra == "testing"
Requires-Dist: pytest-cov>=2.0; extra == "testing"
Requires-Dist: mypy>=0.910; extra == "testing"
Requires-Dist: flake8>=3.9; extra == "testing"
Requires-Dist: tox>=3.24; extra == "testing"
Dynamic: author-email
Dynamic: description
Dynamic: description-content-type
Dynamic: home-page
Dynamic: license-file
Dynamic: project-url
